{
    "YourIP":"",
    "JackettIP":"",
    "JackettAPIKEY":"",
    "FTPip":"",
    "FTPport":,
    "FTPusername":"",
    "FTPPassword":"",
    "quackyosUsername":"",
    "quackyosPassword":"",
    "QbittorrentPath":"C:/Program Files (x86)/qBittorrent/qbittorrent.exe",
    "QbittorrentHostIP":"localhost",
    "QbittorrentPort":8080,
    "QbittorrentUsername":"admin",
    "QbittorrentPassword":"",
    "StalledTorrentTimeout":240,
    "LowSpeedTorrentMBs":0.1,
    "PlexRequestSendTimerSeconds":20,
    "ReleaseRangeDays":365,
    "DelayedReleaseDays":45,
    "JackettPath":"C:/ProgramData/Jackett/JackettTray.exe",
    "TorrentSaveLocation":"",
    "WindscribePath":"C:/Program Files/Windscribe/windscribe-cli.exe"
}